[
    {
        "frame": 1,
        "angles": {
            "elbow_angle": 108.02,
            "knee_angle": 171.45,
            "shoulder_tilt": 66.44,
            "hip_angle": 171.45,
            "head_tilt": 12.2
        }
    },
    {
        "frame": 2,
        "angles": {
            "elbow_angle": 77.65,
            "knee_angle": 153.57,
            "shoulder_tilt": 61.02,
            "hip_angle": 153.57,
            "head_tilt": 5.24
        }
    },
    {
        "frame": 3,
        "angles": {
            "elbow_angle": 125.13,
            "knee_angle": 162.27,
            "shoulder_tilt": 55.49,
            "hip_angle": 162.27,
            "head_tilt": 153.49
        }
    },
    {
        "frame": 4,
        "angles": {
            "elbow_angle": 125.93,
            "knee_angle": 177.2,
            "shoulder_tilt": 51.93,
            "hip_angle": 177.2,
            "head_tilt": 101.97
        }
    },
    {
        "frame": 5,
        "angles": {
            "elbow_angle": 114.97,
            "knee_angle": 172.85,
            "shoulder_tilt": 49.94,
            "hip_angle": 172.85,
            "head_tilt": 116.14
        }
    },
    {
        "frame": 6,
        "angles": {
            "elbow_angle": 149.34,
            "knee_angle": 165.85,
            "shoulder_tilt": 60.68,
            "hip_angle": 165.85,
            "head_tilt": 140.76
        }
    },
    {
        "frame": 7,
        "angles": {
            "elbow_angle": 146.54,
            "knee_angle": 153.03,
            "shoulder_tilt": 60.76,
            "hip_angle": 153.03,
            "head_tilt": 141.67
        }
    },
    {
        "frame": 8,
        "angles": {
            "elbow_angle": 126.34,
            "knee_angle": 143.95,
            "shoulder_tilt": 62.91,
            "hip_angle": 143.95,
            "head_tilt": 149.99
        }
    },
    {
        "frame": 9,
        "angles": {
            "elbow_angle": 129.67,
            "knee_angle": 120.86,
            "shoulder_tilt": 63.92,
            "hip_angle": 120.86,
            "head_tilt": 147.64
        }
    },
    {
        "frame": 10,
        "angles": {
            "elbow_angle": 121.14,
            "knee_angle": 120.54,
            "shoulder_tilt": 66.64,
            "hip_angle": 120.54,
            "head_tilt": 146.01
        }
    }
]